LogLoader.py
LogLoader-1.0.0.dist-info/METADATA
LogLoader-1.0.0.dist-info/WHEEL
LogLoader-1.0.0.dist-info/top_level.txt
LogLoader-1.0.0.dist-info/RECORD
