Metadata-Version: 2.1
Name: LogLoader
Version: 1.0.0
Summary: Log Export
Author: SINTT
Author-email: bbhh66606@gmail.com
Requires-Dist: pyodbc
Requires-Dist: Pillow
